grouphug/__init__.py
grouphug/collator.py
grouphug/config.py
grouphug/dataset_collection.py
grouphug/dataset_formatter.py
grouphug/heads/__init__.py
grouphug/heads/base.py
grouphug/heads/classification.py
grouphug/heads/lm.py
grouphug/model.py
grouphug/trainer.py
grouphug/utils.py
grouphug-0.8.0.dist-info/LICENSE
grouphug-0.8.0.dist-info/WHEEL
grouphug-0.8.0.dist-info/METADATA
grouphug-0.8.0.dist-info/RECORD
