Metadata-Version: 2.1
Name: grouphug
Version: 0.8.0
Summary: GroupHug is a library with extensions to 🤗 transformers for multitask language modelling.
Home-page: https://github.com/sanderland/grouphug
License: Apache2
Keywords: transformers,language modelling,machine learning,classification
Author: Sander Land
Requires-Python: >=3.8,<4.0
Classifier: License :: Other/Proprietary License
Classifier: Programming Language :: Python :: 3
Classifier: Programming Language :: Python :: 3.8
Classifier: Programming Language :: Python :: 3.9
Classifier: Programming Language :: Python :: 3.10
Classifier: Programming Language :: Python :: 3.11
Requires-Dist: Unidecode (>=1.3.4,<2.0.0)
Requires-Dist: datasets (>=2.0.0,<3.0.0)
Requires-Dist: demoji (>=1.1.0,<2.0.0)
Requires-Dist: evaluate (>=0.3.0,<0.4.0)
Requires-Dist: numpy (>=1.21,<2.0)
Requires-Dist: regex (>=2022.3.15,<2023.0.0)
Requires-Dist: sentencepiece (>=0.1.96,<0.2.0)
Requires-Dist: torch (>=1.10.0,<2.0.0)
Requires-Dist: transformers (>=4.20.0,<5.0.0)
